<?xml version="1.0" encoding="UTF-8" standalone="yes"?>
<addon id="plugin.program.709pair" name="[B][COLOR=gray]709[/COLOR][/B]Pair" version="1.2" provider-name="Tonkapug">
  <requires>
    <import addon="xbmc.python" version="2.19.0"/>
  </requires>
  <extension point="xbmc.python.script" library="addon.py">
    <provides>executable</provides>
  </extension>
  <extension point="xbmc.addon.metadata">
    <platform>all</platform>
    <summary lang="en">Real-Debrid and Trakt Pairing Utility</summary>
    <description lang="en">Real-Debrid and Trakt Pairing</description>
	<disclaimer lang="en">The author is not responsible for the use of this addon. The author is not responsible for the content found using this addon. The author does not host or own any content found within this addon.[CR]The author is in no way affiliated with Kodi, Team Kodi, or the XBMC Foundation.[CR]This is a Non-profit resource, organized solely for educational purposes which is protected under the Fair-Use doctrine of the Copyright Act, Specifically section 107, which does promote freedom of expression, by permitting the unlicensed use of copyright-protected works.</disclaimer>
        <license>Free!!</license>
  </extension>
</addon>
